yosai_dpcache/__init__.py
yosai_dpcache/cache/__init__.py
yosai_dpcache/cache/api.py
yosai_dpcache/cache/cachehandler.py
yosai_dpcache/cache/compat.py
yosai_dpcache/cache/exception.py
yosai_dpcache/cache/proxy.py
yosai_dpcache/cache/proxybackend.py
yosai_dpcache/cache/region.py
yosai_dpcache/cache/settings.py
yosai_dpcache/cache/util.py
yosai_dpcache/cache/backends/__init__.py
yosai_dpcache/cache/backends/null.py
yosai_dpcache/cache/backends/redis.py
yosai_dpcache/cache/conf/__init__.py
yosai_dpcache/cache/plugins/__init__.py
yosai_dpcache/dogpile/__init__.py
yosai_dpcache/dogpile/core/__init__.py
yosai_dpcache/dogpile/core/dogpile.py
yosai_dpcache/dogpile/core/legacy.py
yosai_dpcache/dogpile/core/nameregistry.py
yosai_dpcache/dogpile/core/readwrite_lock.py
yosai_dpcache/dogpile/core/util.py
yosai_dpcache-0.3.0.dist-info/DESCRIPTION.rst
yosai_dpcache-0.3.0.dist-info/METADATA
yosai_dpcache-0.3.0.dist-info/RECORD
yosai_dpcache-0.3.0.dist-info/WHEEL
yosai_dpcache-0.3.0.dist-info/metadata.json
yosai_dpcache-0.3.0.dist-info/top_level.txt
