Metadata-Version: 2.0
Name: yosai-dpcache
Version: 0.3.0
Summary: A caching integration for Yosai
Home-page: http://www.github.com/yosaiproject/yosai_dpcache
Author: Darin Gordon
Author-email: dkcdkg@gmail.com
License: Apache License 2.0
Keywords: caching yosai
Platform: UNKNOWN
Classifier: Development Status :: 4 - Beta
Classifier: Intended Audience :: Developers
Classifier: License :: OSI Approved :: Apache Software License
Classifier: Programming Language :: Python
Classifier: Programming Language :: Python :: 3
Classifier: Programming Language :: Python :: 3.4
Classifier: Programming Language :: Python :: 3.5
Classifier: Topic :: Security
Classifier: Topic :: Software Development :: Libraries :: Application Frameworks
Classifier: Topic :: Software Development :: Libraries :: Python Modules
Requires-Dist: yosai
Requires-Dist: redis
